{
  "id": "cimislia-mereni-none",
  "search": "",
  "address": {
    "district": "cimislia",
    "city": "mereni",
    "building": ""
  },
  "name": {
    "ro": "Institutia Publica Scoala Primara-Gradinita Mereni",
    "ru": ""
  },
  "bac": [],
  "langs": [
    "romana"
  ],
  "profiles": [],
  "phones": [
    "024153225"
  ],
  "type": "Alte",
  "idnp": "1014620008781",
  "directors": [
    {
      "name": "MEDONI MARIA, TEL.FIX: 0241-53-2-40\r\n0241-53-2-25",
      "year": "2017"
    }
  ],
  "teachers": [
    {
      "number": 3,
      "year": "2017"
    }
  ],
  "students": [
    {
      "number": 24,
      "year": "2017"
    }
  ],
  "equipment": [
    {
      "pc": 0,
      "notebook": 1,
      "netbook": 0,
      "tabletPC": 0,
      "proector": 1,
      "interactiveTable": 0,
      "year": "2017"
    }
  ]
}