{
  "id": "floresti-stefanesti-liceul",
  "search": "stefanesti",
  "address": {
    "district": "floresti",
    "city": "stefanesti"
  },
  "name": {
    "ro": "liceul teoretic stefanesti",
    "ru": ""
  },
  "bac": [
    {
      "year": "2015",
      "text": "246   FLOREŞTI       ŞTEFĂNEŞTI          Liceul Teoretic Ştefăneşti                                            22    14    8   63.64   6.14",
      "candidats": 22,
      "rejectedCandidats": 8,
      "mediumNote": 6.14
    },
    {
      "year": "2016",
      "text": "268   FLOREŞTI       ŞTEFĂNEŞTI       Liceul Teoretic Ştefăneşti                                          17   13    4   76,47   6,42",
      "candidats": 17,
      "rejectedCandidats": 4,
      "mediumNote": 6.42
    },
    {
      "year": "2016 all",
      "text": "187   FLOREŞTI       ŞTEFĂNEŞTI        Liceul Teoretic Ştefăneşti                                       19    14    5   73,68   6,32",
      "candidats": 19,
      "rejectedCandidats": 5,
      "mediumNote": 6.32
    },
    {
      "year": "2017",
      "text": "207   FLOREŞTI       ŞTEFĂNEŞTI      Liceul Teoretic Ştefăneşti                                             17   15    2   88,24   6,30",
      "candidats": 17,
      "rejectedCandidats": 2,
      "mediumNote": 6.3
    }
  ],
  "langs": [
    "romana"
  ],
  "profiles": [
    "real",
    "umanist"
  ]
}
