{
  "id": "riscani-hiliuti-none",
  "search": "",
  "address": {
    "district": "riscani",
    "city": "hiliuti",
    "building": ""
  },
  "name": {
    "ro": "Gimnaziul Hiliuţi",
    "ru": ""
  },
  "bac": [],
  "langs": [
    "romana"
  ],
  "profiles": [],
  "phones": [
    "256-45-2-93"
  ],
  "type": "Gimnaziu",
  "idnp": "1013620000308",
  "directors": [
    {
      "name": "Matei Ana, tel.256-45-453,mobil - 068854588",
      "year": "2017"
    }
  ],
  "teachers": [
    {
      "number": 14,
      "year": "2017"
    }
  ],
  "students": [
    {
      "number": 122,
      "year": "2017"
    }
  ],
  "equipment": [
    {
      "pc": 15,
      "notebook": 4,
      "netbook": 0,
      "tabletPC": 0,
      "proector": 2,
      "interactiveTable": 1,
      "year": "2017"
    }
  ]
}